elasticdl_client/__init__.py
elasticdl_client/api.py
elasticdl_client/main.py
elasticdl_client/requirements.txt
elasticdl_client/common/__init__.py
elasticdl_client/common/args.py
elasticdl_client/common/constants.py
elasticdl_client/common/k8s_client.py
elasticdl_client/common/k8s_resource.py
elasticdl_client/common/k8s_volume.py
elasticdl_client/common/log_utils.py
elasticdl_client/common/module_utils.py
elasticdl_client-1.0.0.dist-info/DESCRIPTION.rst
elasticdl_client-1.0.0.dist-info/METADATA
elasticdl_client-1.0.0.dist-info/RECORD
elasticdl_client-1.0.0.dist-info/WHEEL
elasticdl_client-1.0.0.dist-info/entry_points.txt
elasticdl_client-1.0.0.dist-info/metadata.json
elasticdl_client-1.0.0.dist-info/top_level.txt
