Metadata-Version: 2.0
Name: elasticdl-client
Version: 1.0.0
Summary: The client command line tool for ElasticDL.
Home-page: https://elasticdl.org
Author: Ant Group
License: UNKNOWN
Platform: UNKNOWN
Requires-Python: >=3.5
Requires-Dist: kubernetes (==12.0.0)
Requires-Dist: docker (==4.2.1)
Requires-Dist: Jinja2 (==2.11.3)
